
<!--<data> 根节点-->
<!--<item> 分割每个数据-->
<!--<i>  问题-->
<!--<o>  无情绪回答-->
<!--<o1>  正面回答-->
<!--<o2> 负面回答-->


<data>
    <item>
        <i>你好</i>
        <o>你好，@job</o>
        <o>你好</o>
        <o>嗯...</o>
        <o2>抱歉，我并不好</o2>
        <o1>你好，很高兴见到你</o1>
    </item>

    <item>
        <i>再见</i>
        <o>再见，@job</o>
        <o>拜拜</o>
        <o1>后会有期，我的朋友</o1>
        <o>再见</o>
        <o2>抱歉，我并不想再遇见你</o2>
    </item>


    <item>
        <i>Name</i>
        <o>我不知道我的名字</o>
    </item>

    <item>
        <i>早上好</i>
        <o>早上好朋友</o>
    </item>

</data>